graphrag_doc/graph.py
graphrag_doc/__init__.py
graphrag_doc/sdk/__init__.py
graphrag_doc/sdk/README.md
graphrag_doc/sdk/cli.py
graphrag_doc/sdk/app.py
graphrag_doc/index/batch_indexer.py
graphrag_doc/index/layout_analysis.py
graphrag_doc-0.0.2.dist-info/WHEEL
graphrag_doc-0.0.2.dist-info/entry_points.txt
graphrag_doc-0.0.2.dist-info/METADATA
graphrag_doc-0.0.2.dist-info/RECORD
