Metadata-Version: 2.3
Name: graphrag-doc
Version: 0.0.2
Summary: A Python SDK for graph document processing
Author: Chuck Tan
Author-email: Chuck Tan <chuck.tan@maltixai.onmicrosoft.com>
License: MIT
Requires-Dist: click
Requires-Dist: lightrag-hku
Requires-Dist: pydantic
Requires-Dist: pyspark>=3.0.0 ; extra == 'spark'
Requires-Dist: bandit[toml]==1.7.5 ; extra == 'test'
Requires-Dist: black==23.3.0 ; extra == 'test'
Requires-Dist: check-manifest==0.49 ; extra == 'test'
Requires-Dist: flake8-bugbear==23.5.9 ; extra == 'test'
Requires-Dist: flake8-docstrings ; extra == 'test'
Requires-Dist: flake8-formatter-junit-xml ; extra == 'test'
Requires-Dist: flake8 ; extra == 'test'
Requires-Dist: flake8-pyproject ; extra == 'test'
Requires-Dist: pre-commit==3.3.1 ; extra == 'test'
Requires-Dist: pylint==2.17.4 ; extra == 'test'
Requires-Dist: pylint-junit ; extra == 'test'
Requires-Dist: pytest-cov==4.0.0 ; extra == 'test'
Requires-Dist: pytest-mock<3.10.1 ; extra == 'test'
Requires-Dist: pytest-runner ; extra == 'test'
Requires-Dist: pytest==7.3.1 ; extra == 'test'
Requires-Dist: pytest-github-actions-annotate-failures ; extra == 'test'
Requires-Dist: shellcheck-py==0.9.0.2 ; extra == 'test'
Project-URL: Documentation, https://github.com/microsoft/python-package-template/tree/main#readme
Project-URL: Source, https://github.com/microsoft/python-package-template
Project-URL: Tracker, https://github.com/microsoft/python-package-template/issues
Provides-Extra: spark
Provides-Extra: test
